{"items":{"serializeList":[{"name":"hay","nr":1474608.0},{"name":"wood","nr":389211.0},{"name":"carrot","nr":94432.0},{"name":"pumpkin","nr":175635.0},{"name":"weird_substance","nr":169465.0},{"name":"water","nr":115570.0},{"name":"fertilizer","nr":53795.0},{"name":"power","nr":955.9475000000086}]},"dockedFiles":[{"key":"actions","value":"movement"},{"key":"factory","value":"actions"},{"key":"farms","value":"main"},{"key":"movement","value":"static"},{"key":"tools","value":"factory"}],"minimizedFiles":["actions","docs1"],"openFilePositions":[{"key":"actions","value":{"x":929.260498046875,"y":-1404.7789306640625}},{"key":"factory","value":{"x":929.260498046875,"y":-1404.7789306640625}},{"key":"farms","value":{"x":929.260498046875,"y":-1404.7789306640625}},{"key":"main","value":{"x":-1351.231201171875,"y":1066.5362548828125}},{"key":"movement","value":{"x":929.260498046875,"y":-1404.7789306640625}},{"key":"static","value":{"x":2450.656005859375,"y":1555.9268798828125}},{"key":"Test","value":{"x":1389.3341064453125,"y":-991.9256591796875}},{"key":"TODO","value":{"x":-2065.654052734375,"y":163.3282470703125}},{"key":"tools","value":{"x":929.260498046875,"y":-1404.7789306640625}},{"key":"docs0","value":{"x":1380.760986328125,"y":-244.014404296875}},{"key":"f0","value":{"x":-2141.479248046875,"y":-435.9439697265625}},{"key":"docs1","value":{"x":382.886962890625,"y":-228.192626953125}}],"openFileScrollPositions":[{"key":"actions","value":90.41873168945313},{"key":"factory","value":694.776611328125},{"key":"farms","value":-0.0006103515625},{"key":"main","value":36.11054229736328},{"key":"movement","value":-0.00048828125},{"key":"static","value":549.999267578125},{"key":"Test","value":0.0006103515625},{"key":"TODO","value":1.034515380859375},{"key":"tools","value":0.00146484375},{"key":"f0","value":0.0}],"openFileSizes":[{"key":"actions","value":{"x":0.0,"y":1939.81787109375}},{"key":"factory","value":{"x":0.0,"y":1027.317626953125}},{"key":"farms","value":{"x":0.0,"y":1624.1837158203125}},{"key":"main","value":{"x":0.0,"y":684.4298706054688}},{"key":"movement","value":{"x":0.0,"y":1169.1212158203125}},{"key":"static","value":{"x":1229.8145751953125,"y":1708.824951171875}},{"key":"Test","value":{"x":795.6867065429688,"y":683.4238891601563}},{"key":"TODO","value":{"x":0.0,"y":576.436279296875}},{"key":"tools","value":{"x":0.0,"y":1248.5853271484375}},{"key":"docs0","value":{"x":900.0,"y":700.0}},{"key":"f0","value":{"x":0.0,"y":0.0}},{"key":"docs1","value":{"x":900.0,"y":700.0}}],"openDocPages":[{"key":"docs0","value":"docs/output.md"},{"key":"docs1","value":"docs/unlocks/sunflowers.md"}],"unlocks":["grass_9","soil","harvest","pass","do_a_flip","pet_the_piggy","grassland","hay","straw_hat","while","true","false","break","continue","loops","traffic_cone","speed_5","can_harvest","if","else","elif","expand_7","move","north","south","east","west","for","range","get_world_size","wood","bush","entities","clear","plant","change_hat","gray_hat","purple_hat","green_hat","brown_hat","hats","print","quick_print","unlocks","str","debug","carrots_7","carrot","till","can_trade","trade","items","carrot_seed","and","or","not","operators","variables","get_entity_type","get_ground_type","grounds","get_pos_x","get_pos_y","none","num_items","num_unlocked","senses","watering_7","water","use_item","get_water","functions","def","return","global","tree_hat","carrot_hat","append","remove","pop","insert","len","list","lists","from","import","sunflower_seed","sunflower","power","get_active_power","measure","sunflowers","fertilizer_4","weird_substance","trees_8","tree","pumpkins_5","pumpkin","pumpkin_seed","dead_pumpkin","wizard_hat","dicts","sets","add","dict","set","dictionaries","get_cost","costs","get_companion","polyculture","swap","cactus_seed","cactus","unlock","auto_unlock","min","max","abs","random","utilities","get_time","get_tick_count","timing","hedge","treasure","gold","can_move","mazes","sunflower_hat"],"version":3}